[
  {
    "Id": "ac94a920-126d-4149-9f85-98b9c7b47980",
    "UserName": "admin@drivehub.au",
    "NormalizedUserName": "ADMIN@DRIVEHUB.AU",
    "Email": "admin@drivehub.au",
    "NormalizedEmail": "ADMIN@DRIVEHUB.AU",
    "EmailConfirmed": "1",
    "PasswordHash": "AQAAAAIAAYagAAAAEDQrg6Kb4LXN7PuiiLuXd4wcrq6dIBm5+Kq/htZ/6TUEDThc0yGE7HLCjAyKjlIIaQ==",
    "SecurityStamp": "BYJGPCU4OJG67DSIGGOXTARSTAPZ4LU6",
    "ConcurrencyStamp": "ec7822c3-44df-45b7-97c6-3e9f12356a46",
    "PhoneNumber": null,
    "PhoneNumberConfirmed": "0",
    "TwoFactorEnabled": "0",
    "LockoutEnd": null,
    "LockoutEnabled": "1",
    "AccessFailedCount": 0
  }
]